{"nodes": [{"id": "c_users_uset_desktop_work_projects_software_new_folder_inventoryandbilling_src_utils_redis_utils_js", "label": "redis.utils.js", "file_type": "code", "source_file": "C:\\Users\\USET\\Desktop\\WORK\\PROJECTS\\Software\\New folder\\inventoryAndBilling\\src\\utils\\redis.utils.js", "source_location": "L1"}, {"id": "utils_redis_utils_getredisconfig", "label": "getRedisConfig()", "file_type": "code", "source_file": "C:\\Users\\USET\\Desktop\\WORK\\PROJECTS\\Software\\New folder\\inventoryAndBilling\\src\\utils\\redis.utils.js", "source_location": "L8"}, {"id": "utils_redis_utils_createredisclient", "label": "createRedisClient()", "file_type": "code", "source_file": "C:\\Users\\USET\\Desktop\\WORK\\PROJECTS\\Software\\New folder\\inventoryAndBilling\\src\\utils\\redis.utils.js", "source_location": "L21"}, {"id": "utils_redis_utils_getredisclient", "label": "getRedisClient()", "file_type": "code", "source_file": "C:\\Users\\USET\\Desktop\\WORK\\PROJECTS\\Software\\New folder\\inventoryAndBilling\\src\\utils\\redis.utils.js", "source_location": "L49"}, {"id": "utils_redis_utils_closeredisclient", "label": "closeRedisClient()", "file_type": "code", "source_file": "C:\\Users\\USET\\Desktop\\WORK\\PROJECTS\\Software\\New folder\\inventoryAndBilling\\src\\utils\\redis.utils.js", "source_location": "L54"}], "edges": [{"source": "c_users_uset_desktop_work_projects_software_new_folder_inventoryandbilling_src_utils_redis_utils_js", "target": "utils_redis_utils_getredisconfig", "relation": "contains", "confidence": "EXTRACTED", "source_file": "C:\\Users\\USET\\Desktop\\WORK\\PROJECTS\\Software\\New folder\\inventoryAndBilling\\src\\utils\\redis.utils.js", "source_location": "L8", "weight": 1.0}, {"source": "c_users_uset_desktop_work_projects_software_new_folder_inventoryandbilling_src_utils_redis_utils_js", "target": "utils_redis_utils_createredisclient", "relation": "contains", "confidence": "EXTRACTED", "source_file": "C:\\Users\\USET\\Desktop\\WORK\\PROJECTS\\Software\\New folder\\inventoryAndBilling\\src\\utils\\redis.utils.js", "source_location": "L21", "weight": 1.0}, {"source": "c_users_uset_desktop_work_projects_software_new_folder_inventoryandbilling_src_utils_redis_utils_js", "target": "utils_redis_utils_getredisclient", "relation": "contains", "confidence": "EXTRACTED", "source_file": "C:\\Users\\USET\\Desktop\\WORK\\PROJECTS\\Software\\New folder\\inventoryAndBilling\\src\\utils\\redis.utils.js", "source_location": "L49", "weight": 1.0}, {"source": "c_users_uset_desktop_work_projects_software_new_folder_inventoryandbilling_src_utils_redis_utils_js", "target": "utils_redis_utils_closeredisclient", "relation": "contains", "confidence": "EXTRACTED", "source_file": "C:\\Users\\USET\\Desktop\\WORK\\PROJECTS\\Software\\New folder\\inventoryAndBilling\\src\\utils\\redis.utils.js", "source_location": "L54", "weight": 1.0}, {"source": "utils_redis_utils_getredisclient", "target": "utils_redis_utils_createredisclient", "relation": "calls", "confidence": "EXTRACTED", "source_file": "C:\\Users\\USET\\Desktop\\WORK\\PROJECTS\\Software\\New folder\\inventoryAndBilling\\src\\utils\\redis.utils.js", "source_location": "L51", "weight": 1.0}], "raw_calls": [{"caller_nid": "utils_redis_utils_createredisclient", "callee": "catch", "is_member_call": true, "source_file": "C:\\Users\\USET\\Desktop\\WORK\\PROJECTS\\Software\\New folder\\inventoryAndBilling\\src\\utils\\redis.utils.js", "source_location": "L25"}, {"caller_nid": "utils_redis_utils_createredisclient", "callee": "(async () => {\r\n    const client = new Redis(getRedisConfig());\r\n\r\n    client.on('error', (error) => {\r\n      logger.error('Redis client error', { error: error.message });\r\n    });\r\n\r\n    client.on('ready', () => {\r\n      logger.info('Redis connected');\r\n    });\r\n\r\n    await client.connect();\r\n    redisClient = client;\r\n    connecting = null;\r\n    return redisClient;\r\n  })", "is_member_call": false, "source_file": "C:\\Users\\USET\\Desktop\\WORK\\PROJECTS\\Software\\New folder\\inventoryAndBilling\\src\\utils\\redis.utils.js", "source_location": "L25"}, {"caller_nid": "utils_redis_utils_closeredisclient", "callee": "quit", "is_member_call": true, "source_file": "C:\\Users\\USET\\Desktop\\WORK\\PROJECTS\\Software\\New folder\\inventoryAndBilling\\src\\utils\\redis.utils.js", "source_location": "L56"}]}